oralb_ble/__init__.py
oralb_ble/const.py
oralb_ble/parser.py
oralb_ble/py.typed
oralb_ble-1.0.2.dist-info/METADATA
oralb_ble-1.0.2.dist-info/WHEEL
oralb_ble-1.0.2.dist-info/licenses/LICENSE
oralb_ble-1.0.2.dist-info/RECORD
