Metadata-Version: 2.4
Name: oralb-ble
Version: 1.0.2
Summary: Bluetooth library for Oral B devices
License: MIT
License-File: LICENSE
Author: J. Nick Koston
Author-email: bluetooth@koston.org
Requires-Python: >=3.9,<4.0
Classifier: Development Status :: 2 - Pre-Alpha
Classifier: Intended Audience :: Developers
Classifier: License :: OSI Approved :: MIT License
Classifier: Natural Language :: English
Classifier: Operating System :: OS Independent
Classifier: Programming Language :: Python :: 3
Classifier: Programming Language :: Python :: 3.9
Classifier: Programming Language :: Python :: 3.10
Classifier: Programming Language :: Python :: 3.11
Classifier: Programming Language :: Python :: 3.12
Classifier: Programming Language :: Python :: 3.13
Classifier: Programming Language :: Python :: 3.14
Classifier: Topic :: Software Development :: Libraries
Provides-Extra: docs
Requires-Dist: Sphinx (>=5,<8) ; extra == "docs"
Requires-Dist: bleak (>=0.19.2)
Requires-Dist: bleak-retry-connector (>=2.13.0)
Requires-Dist: bluetooth-data-tools (>=0.1.2)
Requires-Dist: bluetooth-sensor-state-data (>=1.6.0)
Requires-Dist: home-assistant-bluetooth (>=1.6.0)
Requires-Dist: myst-parser (>=0.18,<3.1) ; extra == "docs"
Requires-Dist: sphinx-rtd-theme (>=1,<4) ; extra == "docs"
Project-URL: Bug Tracker, https://github.com/Bluetooth-Devices/oralb-ble/issues
Project-URL: Changelog, https://github.com/Bluetooth-Devices/oralb-ble/blob/main/CHANGELOG.md
Project-URL: Documentation, https://oralb-ble.readthedocs.io
Project-URL: Repository, https://github.com/Bluetooth-Devices/oralb-ble
